{
    "Name": "电力活塞IV", //物品名
    "Description": "机器的基本机械零件。用于制作机械臂,也用于制作：捕鱼机，压缩机，卷板机，提取机，压模器，车床，研磨机，流体提取机，精密激光蚀刻机，冲压机床，锻造锤，筛选器。但LuV及其以上级别的电动活塞需要相应低级别的电动活塞之后使用装配线来制作。", //物品描述
    "Category": "ArtisanGoods", //物品类型
	"CategoryTextOverride": "材料：核心部件", //类型文本覆盖
    "Edibility": -300, //食用性-300为不可食用
    "Price": 50, //价格
    "IsColored": false, //颜色取样
    "Recipe": null, //配方
    "NameLocalization": //翻译名称
    {
        //"es": "",
        //"ko": "",
        //"de": "",
        //"fr": "",
        //"hu": "",
        //"it": "",
        //"ja": "",
        //"pt": "",
        //"ru": "",
        //"tr": "",
        //"en": "",
    },
    "DescriptionLocalization": //翻译描述
    {
      //"es": "",
      //"ko": "",
      //"de": "",
      //"fr": "",
      //"hu": "",
      //"it": "",
      //"ja": "",
      //"pt": "",
      //"ru": "",
      //"tr": "",
      //"en": "",
    }
}
